ldt_client_helper/__init__.py
ldt_client_helper/service_account_client.py
ldt_client_helper-1.0.0.dist-info/METADATA
ldt_client_helper-1.0.0.dist-info/WHEEL
ldt_client_helper-1.0.0.dist-info/top_level.txt
ldt_client_helper-1.0.0.dist-info/RECORD
